README.rst
setup.py
device/__init__.py
device/device_info.py
device.egg-info/PKG-INFO
device.egg-info/SOURCES.txt
device.egg-info/dependency_links.txt
device.egg-info/not-zip-safe
device.egg-info/requires.txt
device.egg-info/top_level.txt