Metadata-Version: 1.0
Name: device
Version: 0.1
Summary: it just a test!
Home-page: UNKNOWN
Author: wangdaye
Author-email: 919010348@qq.com
License: BSD
Platform: UNKNOWN
Classifier: Development Status :: 3 - Alpha
Classifier: Environment :: Web Environment
Classifier: Intended Audience :: Developers
Classifier: License :: OSI Approved :: BSD License
Classifier: Operating System :: OS Independent
Classifier: Programming Language :: Python
Classifier: Framework :: Django
